[
  {
    "description": "  As a user I want to buy different sorts of coffee",
    "elements": [
      {
        "id": "coffee-machine;use-coffee-machine-to-buy-different-sorts-of-coffee",
        "keyword": "Scenario",
        "line": 17,
        "name": "Use coffee-machine to buy different sorts of coffee",
        "steps": [
          {
            "arguments": [],
            "keyword": "Given ",
            "name": "that the machine is plugged in",
            "result": {
              "status": "passed",
              "duration": 843080
            },
            "line": 5,
            "match": {
              "location": "/Users/lisa/Desktop/JavaScript-kurs/coffeeMachine/cucumber-exempel-2/coffee-machine/step-definitions/coffee-machine.js:36"
            }
          },
          {
            "arguments": [],
            "keyword": "And ",
            "name": "that water is available",
            "result": {
              "status": "passed",
              "duration": 170415
            },
            "line": 6,
            "match": {
              "location": "/Users/lisa/Desktop/JavaScript-kurs/coffeeMachine/cucumber-exempel-2/coffee-machine/step-definitions/coffee-machine.js:53"
            }
          },
          {
            "arguments": [],
            "keyword": "And ",
            "name": "that the machine has lactosfree milk",
            "result": {
              "status": "passed",
              "duration": 278062
            },
            "line": 7,
            "match": {
              "location": "/Users/lisa/Desktop/JavaScript-kurs/coffeeMachine/cucumber-exempel-2/coffee-machine/step-definitions/coffee-machine.js:87"
            }
          },
          {
            "arguments": [],
            "keyword": "Given ",
            "name": "has enough coffeebeans to grind",
            "result": {
              "status": "passed",
              "duration": 175601
            },
            "line": 10,
            "match": {
              "location": "/Users/lisa/Desktop/JavaScript-kurs/coffeeMachine/cucumber-exempel-2/coffee-machine/step-definitions/coffee-machine.js:95"
            }
          },
          {
            "arguments": [],
            "keyword": "When ",
            "name": "the user chooses from the menu",
            "result": {
              "status": "passed",
              "duration": 176375
            },
            "line": 11,
            "match": {
              "location": "/Users/lisa/Desktop/JavaScript-kurs/coffeeMachine/cucumber-exempel-2/coffee-machine/step-definitions/coffee-machine.js:115"
            }
          },
          {
            "arguments": [],
            "keyword": "And ",
            "name": "the user pays the 20 kr",
            "result": {
              "status": "passed",
              "duration": 192069
            },
            "line": 12,
            "match": {
              "location": "/Users/lisa/Desktop/JavaScript-kurs/coffeeMachine/cucumber-exempel-2/coffee-machine/step-definitions/coffee-machine.js:173"
            }
          },
          {
            "arguments": [],
            "keyword": "Then ",
            "name": "the machine will prepare coffee",
            "result": {
              "status": "passed",
              "duration": 127929
            },
            "line": 13,
            "match": {
              "location": "/Users/lisa/Desktop/JavaScript-kurs/coffeeMachine/cucumber-exempel-2/coffee-machine/step-definitions/coffee-machine.js:242"
            }
          },
          {
            "arguments": [],
            "keyword": "After ",
            "result": {
              "status": "passed",
              "duration": 809209695
            },
            "hidden": true,
            "match": {
              "location": "/Users/lisa/Desktop/JavaScript-kurs/coffeeMachine/cucumber-exempel-2/coffee-machine/node_modules/selenium-cucumber-js/runtime/world.js:250"
            }
          }
        ],
        "tags": [],
        "type": "scenario"
      },
      {
        "id": "coffee-machine;use-coffee-machine-to-buy-different-sorts-of-coffee",
        "keyword": "Scenario",
        "line": 18,
        "name": "Use coffee-machine to buy different sorts of coffee",
        "steps": [
          {
            "arguments": [],
            "keyword": "Given ",
            "name": "that the machine is plugged in",
            "result": {
              "status": "passed",
              "duration": 126195
            },
            "line": 5,
            "match": {
              "location": "/Users/lisa/Desktop/JavaScript-kurs/coffeeMachine/cucumber-exempel-2/coffee-machine/step-definitions/coffee-machine.js:36"
            }
          },
          {
            "arguments": [],
            "keyword": "And ",
            "name": "that water is available",
            "result": {
              "status": "passed",
              "duration": 63824
            },
            "line": 6,
            "match": {
              "location": "/Users/lisa/Desktop/JavaScript-kurs/coffeeMachine/cucumber-exempel-2/coffee-machine/step-definitions/coffee-machine.js:53"
            }
          },
          {
            "arguments": [],
            "keyword": "And ",
            "name": "that the machine has lactosfree milk",
            "result": {
              "status": "passed",
              "duration": 65760
            },
            "line": 7,
            "match": {
              "location": "/Users/lisa/Desktop/JavaScript-kurs/coffeeMachine/cucumber-exempel-2/coffee-machine/step-definitions/coffee-machine.js:87"
            }
          },
          {
            "arguments": [],
            "keyword": "Given ",
            "name": "has enough coffeebeans to grind",
            "result": {
              "status": "passed",
              "duration": 75158
            },
            "line": 10,
            "match": {
              "location": "/Users/lisa/Desktop/JavaScript-kurs/coffeeMachine/cucumber-exempel-2/coffee-machine/step-definitions/coffee-machine.js:95"
            }
          },
          {
            "arguments": [],
            "keyword": "When ",
            "name": "the user chooses from the menu",
            "result": {
              "status": "passed",
              "duration": 48810
            },
            "line": 11,
            "match": {
              "location": "/Users/lisa/Desktop/JavaScript-kurs/coffeeMachine/cucumber-exempel-2/coffee-machine/step-definitions/coffee-machine.js:115"
            }
          },
          {
            "arguments": [],
            "keyword": "And ",
            "name": "the user pays the 20 kr",
            "result": {
              "status": "passed",
              "duration": 75661
            },
            "line": 12,
            "match": {
              "location": "/Users/lisa/Desktop/JavaScript-kurs/coffeeMachine/cucumber-exempel-2/coffee-machine/step-definitions/coffee-machine.js:173"
            }
          },
          {
            "arguments": [],
            "keyword": "Then ",
            "name": "the machine will prepare coffee w milk",
            "result": {
              "status": "passed",
              "duration": 166520
            },
            "line": 13,
            "match": {
              "location": "/Users/lisa/Desktop/JavaScript-kurs/coffeeMachine/cucumber-exempel-2/coffee-machine/step-definitions/coffee-machine.js:253"
            }
          },
          {
            "arguments": [],
            "keyword": "After ",
            "result": {
              "status": "passed",
              "duration": 760869241
            },
            "hidden": true,
            "match": {
              "location": "/Users/lisa/Desktop/JavaScript-kurs/coffeeMachine/cucumber-exempel-2/coffee-machine/node_modules/selenium-cucumber-js/runtime/world.js:250"
            }
          }
        ],
        "tags": [],
        "type": "scenario"
      },
      {
        "id": "coffee-machine;use-coffee-machine-to-buy-different-sorts-of-coffee",
        "keyword": "Scenario",
        "line": 19,
        "name": "Use coffee-machine to buy different sorts of coffee",
        "steps": [
          {
            "arguments": [],
            "keyword": "Given ",
            "name": "that the machine is plugged in",
            "result": {
              "status": "passed",
              "duration": 143917
            },
            "line": 5,
            "match": {
              "location": "/Users/lisa/Desktop/JavaScript-kurs/coffeeMachine/cucumber-exempel-2/coffee-machine/step-definitions/coffee-machine.js:36"
            }
          },
          {
            "arguments": [],
            "keyword": "And ",
            "name": "that water is available",
            "result": {
              "status": "passed",
              "duration": 58990
            },
            "line": 6,
            "match": {
              "location": "/Users/lisa/Desktop/JavaScript-kurs/coffeeMachine/cucumber-exempel-2/coffee-machine/step-definitions/coffee-machine.js:53"
            }
          },
          {
            "arguments": [],
            "keyword": "And ",
            "name": "that the machine has lactosfree milk",
            "result": {
              "status": "passed",
              "duration": 56875
            },
            "line": 7,
            "match": {
              "location": "/Users/lisa/Desktop/JavaScript-kurs/coffeeMachine/cucumber-exempel-2/coffee-machine/step-definitions/coffee-machine.js:87"
            }
          },
          {
            "arguments": [],
            "keyword": "Given ",
            "name": "has enough espressobeans to grind",
            "result": {
              "status": "passed",
              "duration": 132685
            },
            "line": 10,
            "match": {
              "location": "/Users/lisa/Desktop/JavaScript-kurs/coffeeMachine/cucumber-exempel-2/coffee-machine/step-definitions/coffee-machine.js:105"
            }
          },
          {
            "arguments": [],
            "keyword": "When ",
            "name": "the user chooses from the menu",
            "result": {
              "status": "passed",
              "duration": 33651
            },
            "line": 11,
            "match": {
              "location": "/Users/lisa/Desktop/JavaScript-kurs/coffeeMachine/cucumber-exempel-2/coffee-machine/step-definitions/coffee-machine.js:115"
            }
          },
          {
            "arguments": [],
            "keyword": "And ",
            "name": "the user pays the 25 kr",
            "result": {
              "status": "passed",
              "duration": 63846
            },
            "line": 12,
            "match": {
              "location": "/Users/lisa/Desktop/JavaScript-kurs/coffeeMachine/cucumber-exempel-2/coffee-machine/step-definitions/coffee-machine.js:173"
            }
          },
          {
            "arguments": [],
            "keyword": "Then ",
            "name": "the machine will prepare cappucino",
            "result": {
              "status": "passed",
              "duration": 159402
            },
            "line": 13,
            "match": {
              "location": "/Users/lisa/Desktop/JavaScript-kurs/coffeeMachine/cucumber-exempel-2/coffee-machine/step-definitions/coffee-machine.js:264"
            }
          },
          {
            "arguments": [],
            "keyword": "After ",
            "result": {
              "status": "passed",
              "duration": 717466564
            },
            "hidden": true,
            "match": {
              "location": "/Users/lisa/Desktop/JavaScript-kurs/coffeeMachine/cucumber-exempel-2/coffee-machine/node_modules/selenium-cucumber-js/runtime/world.js:250"
            }
          }
        ],
        "tags": [],
        "type": "scenario"
      },
      {
        "id": "coffee-machine;use-coffee-machine-to-buy-different-sorts-of-coffee",
        "keyword": "Scenario",
        "line": 20,
        "name": "Use coffee-machine to buy different sorts of coffee",
        "steps": [
          {
            "arguments": [],
            "keyword": "Given ",
            "name": "that the machine is plugged in",
            "result": {
              "status": "passed",
              "duration": 96149
            },
            "line": 5,
            "match": {
              "location": "/Users/lisa/Desktop/JavaScript-kurs/coffeeMachine/cucumber-exempel-2/coffee-machine/step-definitions/coffee-machine.js:36"
            }
          },
          {
            "arguments": [],
            "keyword": "And ",
            "name": "that water is available",
            "result": {
              "status": "passed",
              "duration": 78330
            },
            "line": 6,
            "match": {
              "location": "/Users/lisa/Desktop/JavaScript-kurs/coffeeMachine/cucumber-exempel-2/coffee-machine/step-definitions/coffee-machine.js:53"
            }
          },
          {
            "arguments": [],
            "keyword": "And ",
            "name": "that the machine has lactosfree milk",
            "result": {
              "status": "passed",
              "duration": 62217
            },
            "line": 7,
            "match": {
              "location": "/Users/lisa/Desktop/JavaScript-kurs/coffeeMachine/cucumber-exempel-2/coffee-machine/step-definitions/coffee-machine.js:87"
            }
          },
          {
            "arguments": [],
            "keyword": "Given ",
            "name": "has enough espressobeans to grind",
            "result": {
              "status": "passed",
              "duration": 47772
            },
            "line": 10,
            "match": {
              "location": "/Users/lisa/Desktop/JavaScript-kurs/coffeeMachine/cucumber-exempel-2/coffee-machine/step-definitions/coffee-machine.js:105"
            }
          },
          {
            "arguments": [],
            "keyword": "When ",
            "name": "the user chooses from the menu",
            "result": {
              "status": "passed",
              "duration": 48660
            },
            "line": 11,
            "match": {
              "location": "/Users/lisa/Desktop/JavaScript-kurs/coffeeMachine/cucumber-exempel-2/coffee-machine/step-definitions/coffee-machine.js:115"
            }
          },
          {
            "arguments": [],
            "keyword": "And ",
            "name": "the user pays the 20 kr",
            "result": {
              "status": "passed",
              "duration": 61662
            },
            "line": 12,
            "match": {
              "location": "/Users/lisa/Desktop/JavaScript-kurs/coffeeMachine/cucumber-exempel-2/coffee-machine/step-definitions/coffee-machine.js:173"
            }
          },
          {
            "arguments": [],
            "keyword": "Then ",
            "name": "the machine will prepare espresso",
            "result": {
              "status": "passed",
              "duration": 160368
            },
            "line": 13,
            "match": {
              "location": "/Users/lisa/Desktop/JavaScript-kurs/coffeeMachine/cucumber-exempel-2/coffee-machine/step-definitions/coffee-machine.js:275"
            }
          },
          {
            "arguments": [],
            "keyword": "After ",
            "result": {
              "status": "passed",
              "duration": 772509657
            },
            "hidden": true,
            "match": {
              "location": "/Users/lisa/Desktop/JavaScript-kurs/coffeeMachine/cucumber-exempel-2/coffee-machine/node_modules/selenium-cucumber-js/runtime/world.js:250"
            }
          }
        ],
        "tags": [],
        "type": "scenario"
      },
      {
        "id": "coffee-machine;use-coffee-machine-to-buy-different-sorts-of-coffee",
        "keyword": "Scenario",
        "line": 21,
        "name": "Use coffee-machine to buy different sorts of coffee",
        "steps": [
          {
            "arguments": [],
            "keyword": "Given ",
            "name": "that the machine is plugged in",
            "result": {
              "status": "passed",
              "duration": 128562
            },
            "line": 5,
            "match": {
              "location": "/Users/lisa/Desktop/JavaScript-kurs/coffeeMachine/cucumber-exempel-2/coffee-machine/step-definitions/coffee-machine.js:36"
            }
          },
          {
            "arguments": [],
            "keyword": "And ",
            "name": "that water is available",
            "result": {
              "status": "passed",
              "duration": 59191
            },
            "line": 6,
            "match": {
              "location": "/Users/lisa/Desktop/JavaScript-kurs/coffeeMachine/cucumber-exempel-2/coffee-machine/step-definitions/coffee-machine.js:53"
            }
          },
          {
            "arguments": [],
            "keyword": "And ",
            "name": "that the machine has lactosfree milk",
            "result": {
              "status": "passed",
              "duration": 50418
            },
            "line": 7,
            "match": {
              "location": "/Users/lisa/Desktop/JavaScript-kurs/coffeeMachine/cucumber-exempel-2/coffee-machine/step-definitions/coffee-machine.js:87"
            }
          },
          {
            "arguments": [],
            "keyword": "Given ",
            "name": "has enough espressobeans to grind",
            "result": {
              "status": "passed",
              "duration": 42262
            },
            "line": 10,
            "match": {
              "location": "/Users/lisa/Desktop/JavaScript-kurs/coffeeMachine/cucumber-exempel-2/coffee-machine/step-definitions/coffee-machine.js:105"
            }
          },
          {
            "arguments": [],
            "keyword": "When ",
            "name": "the user chooses from the menu",
            "result": {
              "status": "passed",
              "duration": 33201
            },
            "line": 11,
            "match": {
              "location": "/Users/lisa/Desktop/JavaScript-kurs/coffeeMachine/cucumber-exempel-2/coffee-machine/step-definitions/coffee-machine.js:115"
            }
          },
          {
            "arguments": [],
            "keyword": "And ",
            "name": "the user pays the 25 kr",
            "result": {
              "status": "passed",
              "duration": 46236
            },
            "line": 12,
            "match": {
              "location": "/Users/lisa/Desktop/JavaScript-kurs/coffeeMachine/cucumber-exempel-2/coffee-machine/step-definitions/coffee-machine.js:173"
            }
          },
          {
            "arguments": [],
            "keyword": "Then ",
            "name": "the machine will prepare macchiato",
            "result": {
              "status": "passed",
              "duration": 283730
            },
            "line": 13,
            "match": {
              "location": "/Users/lisa/Desktop/JavaScript-kurs/coffeeMachine/cucumber-exempel-2/coffee-machine/step-definitions/coffee-machine.js:285"
            }
          },
          {
            "arguments": [],
            "keyword": "After ",
            "result": {
              "status": "passed",
              "duration": 880957460
            },
            "hidden": true,
            "match": {
              "location": "/Users/lisa/Desktop/JavaScript-kurs/coffeeMachine/cucumber-exempel-2/coffee-machine/node_modules/selenium-cucumber-js/runtime/world.js:250"
            }
          }
        ],
        "tags": [],
        "type": "scenario"
      },
      {
        "id": "coffee-machine;use-coffee-machine-to-buy-different-sorts-of-coffee",
        "keyword": "Scenario",
        "line": 22,
        "name": "Use coffee-machine to buy different sorts of coffee",
        "steps": [
          {
            "arguments": [],
            "keyword": "Given ",
            "name": "that the machine is plugged in",
            "result": {
              "status": "passed",
              "duration": 102626
            },
            "line": 5,
            "match": {
              "location": "/Users/lisa/Desktop/JavaScript-kurs/coffeeMachine/cucumber-exempel-2/coffee-machine/step-definitions/coffee-machine.js:36"
            }
          },
          {
            "arguments": [],
            "keyword": "And ",
            "name": "that water is available",
            "result": {
              "status": "passed",
              "duration": 61557
            },
            "line": 6,
            "match": {
              "location": "/Users/lisa/Desktop/JavaScript-kurs/coffeeMachine/cucumber-exempel-2/coffee-machine/step-definitions/coffee-machine.js:53"
            }
          },
          {
            "arguments": [],
            "keyword": "And ",
            "name": "that the machine has lactosfree milk",
            "result": {
              "status": "passed",
              "duration": 54280
            },
            "line": 7,
            "match": {
              "location": "/Users/lisa/Desktop/JavaScript-kurs/coffeeMachine/cucumber-exempel-2/coffee-machine/step-definitions/coffee-machine.js:87"
            }
          },
          {
            "arguments": [],
            "keyword": "Given ",
            "name": "has enough espressobeans to grind",
            "result": {
              "status": "passed",
              "duration": 47201
            },
            "line": 10,
            "match": {
              "location": "/Users/lisa/Desktop/JavaScript-kurs/coffeeMachine/cucumber-exempel-2/coffee-machine/step-definitions/coffee-machine.js:105"
            }
          },
          {
            "arguments": [],
            "keyword": "When ",
            "name": "the user chooses from the menu",
            "result": {
              "status": "passed",
              "duration": 34232
            },
            "line": 11,
            "match": {
              "location": "/Users/lisa/Desktop/JavaScript-kurs/coffeeMachine/cucumber-exempel-2/coffee-machine/step-definitions/coffee-machine.js:115"
            }
          },
          {
            "arguments": [],
            "keyword": "And ",
            "name": "the user pays the 30 kr",
            "result": {
              "status": "passed",
              "duration": 59322
            },
            "line": 12,
            "match": {
              "location": "/Users/lisa/Desktop/JavaScript-kurs/coffeeMachine/cucumber-exempel-2/coffee-machine/step-definitions/coffee-machine.js:173"
            }
          },
          {
            "arguments": [],
            "keyword": "Then ",
            "name": "the machine will prepare latte",
            "result": {
              "status": "passed",
              "duration": 155730
            },
            "line": 13,
            "match": {
              "location": "/Users/lisa/Desktop/JavaScript-kurs/coffeeMachine/cucumber-exempel-2/coffee-machine/step-definitions/coffee-machine.js:294"
            }
          },
          {
            "arguments": [],
            "keyword": "After ",
            "result": {
              "status": "passed",
              "duration": 774628780
            },
            "hidden": true,
            "match": {
              "location": "/Users/lisa/Desktop/JavaScript-kurs/coffeeMachine/cucumber-exempel-2/coffee-machine/node_modules/selenium-cucumber-js/runtime/world.js:250"
            }
          }
        ],
        "tags": [],
        "type": "scenario"
      },
      {
        "id": "coffee-machine;use-coffee-machine-to-buy-different-sorts-of-coffee",
        "keyword": "Scenario",
        "line": 23,
        "name": "Use coffee-machine to buy different sorts of coffee",
        "steps": [
          {
            "arguments": [],
            "keyword": "Given ",
            "name": "that the machine is plugged in",
            "result": {
              "status": "passed",
              "duration": 122516
            },
            "line": 5,
            "match": {
              "location": "/Users/lisa/Desktop/JavaScript-kurs/coffeeMachine/cucumber-exempel-2/coffee-machine/step-definitions/coffee-machine.js:36"
            }
          },
          {
            "arguments": [],
            "keyword": "And ",
            "name": "that water is available",
            "result": {
              "status": "passed",
              "duration": 54324
            },
            "line": 6,
            "match": {
              "location": "/Users/lisa/Desktop/JavaScript-kurs/coffeeMachine/cucumber-exempel-2/coffee-machine/step-definitions/coffee-machine.js:53"
            }
          },
          {
            "arguments": [],
            "keyword": "And ",
            "name": "that the machine has lactosfree milk",
            "result": {
              "status": "passed",
              "duration": 51377
            },
            "line": 7,
            "match": {
              "location": "/Users/lisa/Desktop/JavaScript-kurs/coffeeMachine/cucumber-exempel-2/coffee-machine/step-definitions/coffee-machine.js:87"
            }
          },
          {
            "arguments": [],
            "keyword": "Given ",
            "name": "has enough espressobeans to grind",
            "result": {
              "status": "passed",
              "duration": 48398
            },
            "line": 10,
            "match": {
              "location": "/Users/lisa/Desktop/JavaScript-kurs/coffeeMachine/cucumber-exempel-2/coffee-machine/step-definitions/coffee-machine.js:105"
            }
          },
          {
            "arguments": [],
            "keyword": "When ",
            "name": "the user chooses from the menu",
            "result": {
              "status": "passed",
              "duration": 36352
            },
            "line": 11,
            "match": {
              "location": "/Users/lisa/Desktop/JavaScript-kurs/coffeeMachine/cucumber-exempel-2/coffee-machine/step-definitions/coffee-machine.js:115"
            }
          },
          {
            "arguments": [],
            "keyword": "And ",
            "name": "the user pays the 30 kr",
            "result": {
              "status": "passed",
              "duration": 65781
            },
            "line": 12,
            "match": {
              "location": "/Users/lisa/Desktop/JavaScript-kurs/coffeeMachine/cucumber-exempel-2/coffee-machine/step-definitions/coffee-machine.js:173"
            }
          },
          {
            "arguments": [],
            "keyword": "Then ",
            "name": "the machine will prepare cortado",
            "result": {
              "status": "passed",
              "duration": 198806
            },
            "line": 13,
            "match": {
              "location": "/Users/lisa/Desktop/JavaScript-kurs/coffeeMachine/cucumber-exempel-2/coffee-machine/step-definitions/coffee-machine.js:305"
            }
          },
          {
            "arguments": [],
            "keyword": "After ",
            "result": {
              "status": "passed",
              "duration": 765411179
            },
            "hidden": true,
            "match": {
              "location": "/Users/lisa/Desktop/JavaScript-kurs/coffeeMachine/cucumber-exempel-2/coffee-machine/node_modules/selenium-cucumber-js/runtime/world.js:250"
            }
          }
        ],
        "tags": [],
        "type": "scenario"
      },
      {
        "id": "coffee-machine;buying-a-cappucino",
        "keyword": "Scenario",
        "line": 26,
        "name": "Buying a cappucino",
        "steps": [
          {
            "arguments": [],
            "keyword": "Given ",
            "name": "that the machine is plugged in",
            "result": {
              "status": "passed",
              "duration": 104187
            },
            "line": 5,
            "match": {
              "location": "/Users/lisa/Desktop/JavaScript-kurs/coffeeMachine/cucumber-exempel-2/coffee-machine/step-definitions/coffee-machine.js:36"
            }
          },
          {
            "arguments": [],
            "keyword": "And ",
            "name": "that water is available",
            "result": {
              "status": "passed",
              "duration": 49577
            },
            "line": 6,
            "match": {
              "location": "/Users/lisa/Desktop/JavaScript-kurs/coffeeMachine/cucumber-exempel-2/coffee-machine/step-definitions/coffee-machine.js:53"
            }
          },
          {
            "arguments": [],
            "keyword": "And ",
            "name": "that the machine has lactosfree milk",
            "result": {
              "status": "passed",
              "duration": 52747
            },
            "line": 7,
            "match": {
              "location": "/Users/lisa/Desktop/JavaScript-kurs/coffeeMachine/cucumber-exempel-2/coffee-machine/step-definitions/coffee-machine.js:87"
            }
          },
          {
            "arguments": [],
            "keyword": "Given ",
            "name": "that the milk is cold enough",
            "result": {
              "status": "passed",
              "duration": 225554
            },
            "line": 27,
            "match": {
              "location": "/Users/lisa/Desktop/JavaScript-kurs/coffeeMachine/cucumber-exempel-2/coffee-machine/step-definitions/coffee-machine.js:317"
            }
          },
          {
            "arguments": [],
            "keyword": "When ",
            "name": "the user chooses a cappucino",
            "result": {
              "status": "passed",
              "duration": 102140
            },
            "line": 28,
            "match": {
              "location": "/Users/lisa/Desktop/JavaScript-kurs/coffeeMachine/cucumber-exempel-2/coffee-machine/step-definitions/coffee-machine.js:327"
            }
          },
          {
            "arguments": [],
            "keyword": "And ",
            "name": "pays the 25 kr",
            "result": {
              "status": "passed",
              "duration": 114570
            },
            "line": 29,
            "match": {
              "location": "/Users/lisa/Desktop/JavaScript-kurs/coffeeMachine/cucumber-exempel-2/coffee-machine/step-definitions/coffee-machine.js:339"
            }
          },
          {
            "arguments": [],
            "keyword": "Then ",
            "name": "the machine will prepare, and serve, a delicious cappucino",
            "result": {
              "status": "passed",
              "duration": 88158
            },
            "line": 30,
            "match": {
              "location": "/Users/lisa/Desktop/JavaScript-kurs/coffeeMachine/cucumber-exempel-2/coffee-machine/step-definitions/coffee-machine.js:352"
            }
          },
          {
            "arguments": [],
            "keyword": "After ",
            "result": {
              "status": "passed",
              "duration": 767107679
            },
            "hidden": true,
            "match": {
              "location": "/Users/lisa/Desktop/JavaScript-kurs/coffeeMachine/cucumber-exempel-2/coffee-machine/node_modules/selenium-cucumber-js/runtime/world.js:250"
            }
          }
        ],
        "tags": [],
        "type": "scenario"
      },
      {
        "id": "coffee-machine;paying-for-coffee-when-user-forgot-his/hers-wallet",
        "keyword": "Scenario",
        "line": 41,
        "name": "Paying for coffee when user forgot his/hers wallet",
        "steps": [
          {
            "arguments": [],
            "keyword": "Given ",
            "name": "that the machine is plugged in",
            "result": {
              "status": "passed",
              "duration": 117072
            },
            "line": 5,
            "match": {
              "location": "/Users/lisa/Desktop/JavaScript-kurs/coffeeMachine/cucumber-exempel-2/coffee-machine/step-definitions/coffee-machine.js:36"
            }
          },
          {
            "arguments": [],
            "keyword": "And ",
            "name": "that water is available",
            "result": {
              "status": "passed",
              "duration": 48220
            },
            "line": 6,
            "match": {
              "location": "/Users/lisa/Desktop/JavaScript-kurs/coffeeMachine/cucumber-exempel-2/coffee-machine/step-definitions/coffee-machine.js:53"
            }
          },
          {
            "arguments": [],
            "keyword": "And ",
            "name": "that the machine has lactosfree milk",
            "result": {
              "status": "passed",
              "duration": 49622
            },
            "line": 7,
            "match": {
              "location": "/Users/lisa/Desktop/JavaScript-kurs/coffeeMachine/cucumber-exempel-2/coffee-machine/step-definitions/coffee-machine.js:87"
            }
          },
          {
            "arguments": [],
            "keyword": "Given ",
            "name": "that the user wants to buy coffee",
            "result": {
              "status": "passed",
              "duration": 222352
            },
            "line": 34,
            "match": {
              "location": "/Users/lisa/Desktop/JavaScript-kurs/coffeeMachine/cucumber-exempel-2/coffee-machine/step-definitions/coffee-machine.js:365"
            }
          },
          {
            "arguments": [],
            "keyword": "When ",
            "name": "the user chooses coffee",
            "result": {
              "status": "passed",
              "duration": 102137
            },
            "line": 35,
            "match": {
              "location": "/Users/lisa/Desktop/JavaScript-kurs/coffeeMachine/cucumber-exempel-2/coffee-machine/step-definitions/coffee-machine.js:377"
            }
          },
          {
            "arguments": [],
            "keyword": "And ",
            "name": "the user pays using swish",
            "result": {
              "status": "passed",
              "duration": 135877
            },
            "line": 36,
            "match": {
              "location": "/Users/lisa/Desktop/JavaScript-kurs/coffeeMachine/cucumber-exempel-2/coffee-machine/step-definitions/coffee-machine.js:389"
            }
          },
          {
            "arguments": [],
            "keyword": "Then ",
            "name": "the machine prepares coffee",
            "result": {
              "status": "passed",
              "duration": 90823
            },
            "line": 37,
            "match": {
              "location": "/Users/lisa/Desktop/JavaScript-kurs/coffeeMachine/cucumber-exempel-2/coffee-machine/step-definitions/coffee-machine.js:414"
            }
          },
          {
            "arguments": [],
            "keyword": "After ",
            "result": {
              "status": "passed",
              "duration": 726497000
            },
            "hidden": true,
            "match": {
              "location": "/Users/lisa/Desktop/JavaScript-kurs/coffeeMachine/cucumber-exempel-2/coffee-machine/node_modules/selenium-cucumber-js/runtime/world.js:250"
            }
          }
        ],
        "tags": [],
        "type": "scenario"
      },
      {
        "id": "coffee-machine;paying-for-coffee-when-user-forgot-his/hers-wallet",
        "keyword": "Scenario",
        "line": 42,
        "name": "Paying for coffee when user forgot his/hers wallet",
        "steps": [
          {
            "arguments": [],
            "keyword": "Given ",
            "name": "that the machine is plugged in",
            "result": {
              "status": "passed",
              "duration": 94236
            },
            "line": 5,
            "match": {
              "location": "/Users/lisa/Desktop/JavaScript-kurs/coffeeMachine/cucumber-exempel-2/coffee-machine/step-definitions/coffee-machine.js:36"
            }
          },
          {
            "arguments": [],
            "keyword": "And ",
            "name": "that water is available",
            "result": {
              "status": "passed",
              "duration": 50469
            },
            "line": 6,
            "match": {
              "location": "/Users/lisa/Desktop/JavaScript-kurs/coffeeMachine/cucumber-exempel-2/coffee-machine/step-definitions/coffee-machine.js:53"
            }
          },
          {
            "arguments": [],
            "keyword": "And ",
            "name": "that the machine has lactosfree milk",
            "result": {
              "status": "passed",
              "duration": 49574
            },
            "line": 7,
            "match": {
              "location": "/Users/lisa/Desktop/JavaScript-kurs/coffeeMachine/cucumber-exempel-2/coffee-machine/step-definitions/coffee-machine.js:87"
            }
          },
          {
            "arguments": [],
            "keyword": "Given ",
            "name": "that the user wants to buy coffee",
            "result": {
              "status": "passed",
              "duration": 50638
            },
            "line": 34,
            "match": {
              "location": "/Users/lisa/Desktop/JavaScript-kurs/coffeeMachine/cucumber-exempel-2/coffee-machine/step-definitions/coffee-machine.js:365"
            }
          },
          {
            "arguments": [],
            "keyword": "When ",
            "name": "the user chooses coffee",
            "result": {
              "status": "passed",
              "duration": 46309
            },
            "line": 35,
            "match": {
              "location": "/Users/lisa/Desktop/JavaScript-kurs/coffeeMachine/cucumber-exempel-2/coffee-machine/step-definitions/coffee-machine.js:377"
            }
          },
          {
            "arguments": [],
            "keyword": "And ",
            "name": "the user pays using card",
            "result": {
              "status": "passed",
              "duration": 158892
            },
            "line": 36,
            "match": {
              "location": "/Users/lisa/Desktop/JavaScript-kurs/coffeeMachine/cucumber-exempel-2/coffee-machine/step-definitions/coffee-machine.js:401"
            }
          },
          {
            "arguments": [],
            "keyword": "Then ",
            "name": "the machine prepares coffee",
            "result": {
              "status": "passed",
              "duration": 65566
            },
            "line": 37,
            "match": {
              "location": "/Users/lisa/Desktop/JavaScript-kurs/coffeeMachine/cucumber-exempel-2/coffee-machine/step-definitions/coffee-machine.js:414"
            }
          },
          {
            "arguments": [],
            "keyword": "After ",
            "result": {
              "status": "passed",
              "duration": 717976150
            },
            "hidden": true,
            "match": {
              "location": "/Users/lisa/Desktop/JavaScript-kurs/coffeeMachine/cucumber-exempel-2/coffee-machine/node_modules/selenium-cucumber-js/runtime/world.js:250"
            }
          }
        ],
        "tags": [],
        "type": "scenario"
      },
      {
        "id": "coffee-machine;the-coffee-machine-is-cleaning-itself-between-uses",
        "keyword": "Scenario",
        "line": 45,
        "name": "The coffee-machine is cleaning itself between uses",
        "steps": [
          {
            "arguments": [],
            "keyword": "Given ",
            "name": "that the machine is plugged in",
            "result": {
              "status": "passed",
              "duration": 97363
            },
            "line": 5,
            "match": {
              "location": "/Users/lisa/Desktop/JavaScript-kurs/coffeeMachine/cucumber-exempel-2/coffee-machine/step-definitions/coffee-machine.js:36"
            }
          },
          {
            "arguments": [],
            "keyword": "And ",
            "name": "that water is available",
            "result": {
              "status": "passed",
              "duration": 50868
            },
            "line": 6,
            "match": {
              "location": "/Users/lisa/Desktop/JavaScript-kurs/coffeeMachine/cucumber-exempel-2/coffee-machine/step-definitions/coffee-machine.js:53"
            }
          },
          {
            "arguments": [],
            "keyword": "And ",
            "name": "that the machine has lactosfree milk",
            "result": {
              "status": "passed",
              "duration": 49340
            },
            "line": 7,
            "match": {
              "location": "/Users/lisa/Desktop/JavaScript-kurs/coffeeMachine/cucumber-exempel-2/coffee-machine/step-definitions/coffee-machine.js:87"
            }
          },
          {
            "arguments": [],
            "keyword": "Given ",
            "name": "that nobody buys coffee",
            "result": {
              "status": "passed",
              "duration": 164072
            },
            "line": 46,
            "match": {
              "location": "/Users/lisa/Desktop/JavaScript-kurs/coffeeMachine/cucumber-exempel-2/coffee-machine/step-definitions/coffee-machine.js:427"
            }
          },
          {
            "arguments": [],
            "keyword": "And ",
            "name": "that it has been 30 min since last cleaning",
            "result": {
              "status": "passed",
              "duration": 129094
            },
            "line": 47,
            "match": {
              "location": "/Users/lisa/Desktop/JavaScript-kurs/coffeeMachine/cucumber-exempel-2/coffee-machine/step-definitions/coffee-machine.js:438"
            }
          },
          {
            "arguments": [],
            "keyword": "Then ",
            "name": "it will use steaming hot water",
            "result": {
              "status": "passed",
              "duration": 199841
            },
            "line": 48,
            "match": {
              "location": "/Users/lisa/Desktop/JavaScript-kurs/coffeeMachine/cucumber-exempel-2/coffee-machine/step-definitions/coffee-machine.js:454"
            }
          },
          {
            "arguments": [],
            "keyword": "And ",
            "name": "the machine will clean itself",
            "result": {
              "status": "passed",
              "duration": 116015
            },
            "line": 49,
            "match": {
              "location": "/Users/lisa/Desktop/JavaScript-kurs/coffeeMachine/cucumber-exempel-2/coffee-machine/step-definitions/coffee-machine.js:464"
            }
          },
          {
            "arguments": [],
            "keyword": "And ",
            "name": "it will take 1 minute",
            "result": {
              "status": "passed",
              "duration": 134975
            },
            "line": 50,
            "match": {
              "location": "/Users/lisa/Desktop/JavaScript-kurs/coffeeMachine/cucumber-exempel-2/coffee-machine/step-definitions/coffee-machine.js:474"
            }
          },
          {
            "arguments": [],
            "keyword": "After ",
            "result": {
              "status": "passed",
              "duration": 716794635
            },
            "hidden": true,
            "match": {
              "location": "/Users/lisa/Desktop/JavaScript-kurs/coffeeMachine/cucumber-exempel-2/coffee-machine/node_modules/selenium-cucumber-js/runtime/world.js:250"
            }
          }
        ],
        "tags": [],
        "type": "scenario"
      },
      {
        "id": "coffee-machine;user-wants-to-buy-coffee-but-there-is-no-water-connected-to-machine",
        "keyword": "Scenario",
        "line": 52,
        "name": "User wants to buy coffee but there is no water connected to machine",
        "steps": [
          {
            "arguments": [],
            "keyword": "Given ",
            "name": "that the machine is plugged in",
            "result": {
              "status": "passed",
              "duration": 73854
            },
            "line": 5,
            "match": {
              "location": "/Users/lisa/Desktop/JavaScript-kurs/coffeeMachine/cucumber-exempel-2/coffee-machine/step-definitions/coffee-machine.js:36"
            }
          },
          {
            "arguments": [],
            "keyword": "And ",
            "name": "that water is available",
            "result": {
              "status": "passed",
              "duration": 40706
            },
            "line": 6,
            "match": {
              "location": "/Users/lisa/Desktop/JavaScript-kurs/coffeeMachine/cucumber-exempel-2/coffee-machine/step-definitions/coffee-machine.js:53"
            }
          },
          {
            "arguments": [],
            "keyword": "And ",
            "name": "that the machine has lactosfree milk",
            "result": {
              "status": "passed",
              "duration": 47180
            },
            "line": 7,
            "match": {
              "location": "/Users/lisa/Desktop/JavaScript-kurs/coffeeMachine/cucumber-exempel-2/coffee-machine/step-definitions/coffee-machine.js:87"
            }
          },
          {
            "arguments": [],
            "keyword": "Given ",
            "name": "that the user wants to buy coffee",
            "result": {
              "status": "passed",
              "duration": 45045
            },
            "line": 53,
            "match": {
              "location": "/Users/lisa/Desktop/JavaScript-kurs/coffeeMachine/cucumber-exempel-2/coffee-machine/step-definitions/coffee-machine.js:365"
            }
          },
          {
            "arguments": [],
            "keyword": "When ",
            "name": "the user sees that the machine isn't connected to water",
            "result": {
              "status": "undefined"
            },
            "line": 54
          },
          {
            "arguments": [],
            "keyword": "Then ",
            "name": "the user goes to buy coffee somewhere else",
            "result": {
              "status": "undefined"
            },
            "line": 55
          },
          {
            "arguments": [],
            "keyword": "After ",
            "result": {
              "status": "passed",
              "duration": 725426962
            },
            "hidden": true,
            "match": {
              "location": "/Users/lisa/Desktop/JavaScript-kurs/coffeeMachine/cucumber-exempel-2/coffee-machine/node_modules/selenium-cucumber-js/runtime/world.js:250"
            }
          }
        ],
        "tags": [],
        "type": "scenario"
      },
      {
        "id": "coffee-machine;user-wants-to-buy-tea-water",
        "keyword": "Scenario",
        "line": 57,
        "name": "User wants to buy tea-water",
        "steps": [
          {
            "arguments": [],
            "keyword": "Given ",
            "name": "that the machine is plugged in",
            "result": {
              "status": "passed",
              "duration": 85595
            },
            "line": 5,
            "match": {
              "location": "/Users/lisa/Desktop/JavaScript-kurs/coffeeMachine/cucumber-exempel-2/coffee-machine/step-definitions/coffee-machine.js:36"
            }
          },
          {
            "arguments": [],
            "keyword": "And ",
            "name": "that water is available",
            "result": {
              "status": "passed",
              "duration": 44382
            },
            "line": 6,
            "match": {
              "location": "/Users/lisa/Desktop/JavaScript-kurs/coffeeMachine/cucumber-exempel-2/coffee-machine/step-definitions/coffee-machine.js:53"
            }
          },
          {
            "arguments": [],
            "keyword": "And ",
            "name": "that the machine has lactosfree milk",
            "result": {
              "status": "passed",
              "duration": 50885
            },
            "line": 7,
            "match": {
              "location": "/Users/lisa/Desktop/JavaScript-kurs/coffeeMachine/cucumber-exempel-2/coffee-machine/step-definitions/coffee-machine.js:87"
            }
          },
          {
            "arguments": [],
            "keyword": "Given ",
            "name": "that the machine is plugged in",
            "result": {
              "status": "passed",
              "duration": 52836
            },
            "line": 58,
            "match": {
              "location": "/Users/lisa/Desktop/JavaScript-kurs/coffeeMachine/cucumber-exempel-2/coffee-machine/step-definitions/coffee-machine.js:36"
            }
          },
          {
            "arguments": [],
            "keyword": "And ",
            "name": "that the machine is connected to water",
            "result": {
              "status": "undefined"
            },
            "line": 59
          },
          {
            "arguments": [],
            "keyword": "When ",
            "name": "the user chooses tea",
            "result": {
              "status": "undefined"
            },
            "line": 60
          },
          {
            "arguments": [],
            "keyword": "Then ",
            "name": "the machine serves hot water",
            "result": {
              "status": "undefined"
            },
            "line": 61
          },
          {
            "arguments": [],
            "keyword": "After ",
            "result": {
              "status": "passed",
              "duration": 724678974
            },
            "hidden": true,
            "match": {
              "location": "/Users/lisa/Desktop/JavaScript-kurs/coffeeMachine/cucumber-exempel-2/coffee-machine/node_modules/selenium-cucumber-js/runtime/world.js:250"
            }
          }
        ],
        "tags": [],
        "type": "scenario"
      },
      {
        "id": "coffee-machine;user-buys-coffee-and-changes-his/her-mind-in-the-middle-of-brewing",
        "keyword": "Scenario",
        "line": 63,
        "name": "User buys coffee and changes his/her mind in the middle of brewing",
        "steps": [
          {
            "arguments": [],
            "keyword": "Given ",
            "name": "that the machine is plugged in",
            "result": {
              "status": "passed",
              "duration": 97090
            },
            "line": 5,
            "match": {
              "location": "/Users/lisa/Desktop/JavaScript-kurs/coffeeMachine/cucumber-exempel-2/coffee-machine/step-definitions/coffee-machine.js:36"
            }
          },
          {
            "arguments": [],
            "keyword": "And ",
            "name": "that water is available",
            "result": {
              "status": "passed",
              "duration": 53193
            },
            "line": 6,
            "match": {
              "location": "/Users/lisa/Desktop/JavaScript-kurs/coffeeMachine/cucumber-exempel-2/coffee-machine/step-definitions/coffee-machine.js:53"
            }
          },
          {
            "arguments": [],
            "keyword": "And ",
            "name": "that the machine has lactosfree milk",
            "result": {
              "status": "passed",
              "duration": 51385
            },
            "line": 7,
            "match": {
              "location": "/Users/lisa/Desktop/JavaScript-kurs/coffeeMachine/cucumber-exempel-2/coffee-machine/step-definitions/coffee-machine.js:87"
            }
          },
          {
            "arguments": [],
            "keyword": "Given ",
            "name": "the user paid and chose coffee",
            "result": {
              "status": "undefined"
            },
            "line": 64
          },
          {
            "arguments": [],
            "keyword": "When ",
            "name": "the user presses the cancel-button",
            "result": {
              "status": "undefined"
            },
            "line": 65
          },
          {
            "arguments": [],
            "keyword": "Then ",
            "name": "the machine immediately stops the brewing",
            "result": {
              "status": "undefined"
            },
            "line": 66
          },
          {
            "arguments": [],
            "keyword": "And ",
            "name": "user then have to pay for new coffee",
            "result": {
              "status": "undefined"
            },
            "line": 67
          },
          {
            "arguments": [],
            "keyword": "After ",
            "result": {
              "status": "passed",
              "duration": 727942827
            },
            "hidden": true,
            "match": {
              "location": "/Users/lisa/Desktop/JavaScript-kurs/coffeeMachine/cucumber-exempel-2/coffee-machine/node_modules/selenium-cucumber-js/runtime/world.js:250"
            }
          }
        ],
        "tags": [],
        "type": "scenario"
      },
      {
        "id": "coffee-machine;user-puts-his/her-hand-down-the-coffee-bean-grinder",
        "keyword": "Scenario",
        "line": 69,
        "name": "User puts his/her hand down the coffee-bean grinder",
        "steps": [
          {
            "arguments": [],
            "keyword": "Given ",
            "name": "that the machine is plugged in",
            "result": {
              "status": "passed",
              "duration": 96688
            },
            "line": 5,
            "match": {
              "location": "/Users/lisa/Desktop/JavaScript-kurs/coffeeMachine/cucumber-exempel-2/coffee-machine/step-definitions/coffee-machine.js:36"
            }
          },
          {
            "arguments": [],
            "keyword": "And ",
            "name": "that water is available",
            "result": {
              "status": "passed",
              "duration": 52343
            },
            "line": 6,
            "match": {
              "location": "/Users/lisa/Desktop/JavaScript-kurs/coffeeMachine/cucumber-exempel-2/coffee-machine/step-definitions/coffee-machine.js:53"
            }
          },
          {
            "arguments": [],
            "keyword": "And ",
            "name": "that the machine has lactosfree milk",
            "result": {
              "status": "passed",
              "duration": 51189
            },
            "line": 7,
            "match": {
              "location": "/Users/lisa/Desktop/JavaScript-kurs/coffeeMachine/cucumber-exempel-2/coffee-machine/step-definitions/coffee-machine.js:87"
            }
          },
          {
            "arguments": [],
            "keyword": "Given ",
            "name": "that user doesn't have all goats in the pen",
            "result": {
              "status": "undefined"
            },
            "line": 70
          },
          {
            "arguments": [],
            "keyword": "When ",
            "name": "user puts hand in coffee grinder",
            "result": {
              "status": "undefined"
            },
            "line": 71
          },
          {
            "arguments": [],
            "keyword": "Then ",
            "name": "users hand grinds up",
            "result": {
              "status": "undefined"
            },
            "line": 72
          },
          {
            "arguments": [],
            "keyword": "And ",
            "name": "the machine stop because of malfunction",
            "result": {
              "status": "undefined"
            },
            "line": 73
          },
          {
            "arguments": [],
            "keyword": "After ",
            "result": {
              "status": "passed",
              "duration": 729302527
            },
            "hidden": true,
            "match": {
              "location": "/Users/lisa/Desktop/JavaScript-kurs/coffeeMachine/cucumber-exempel-2/coffee-machine/node_modules/selenium-cucumber-js/runtime/world.js:250"
            }
          }
        ],
        "tags": [],
        "type": "scenario"
      },
      {
        "id": "coffee-machine;there-is-an-electricity-shortage",
        "keyword": "Scenario",
        "line": 75,
        "name": "There is an electricity-shortage",
        "steps": [
          {
            "arguments": [],
            "keyword": "Given ",
            "name": "that the machine is plugged in",
            "result": {
              "status": "passed",
              "duration": 83316
            },
            "line": 5,
            "match": {
              "location": "/Users/lisa/Desktop/JavaScript-kurs/coffeeMachine/cucumber-exempel-2/coffee-machine/step-definitions/coffee-machine.js:36"
            }
          },
          {
            "arguments": [],
            "keyword": "And ",
            "name": "that water is available",
            "result": {
              "status": "passed",
              "duration": 48156
            },
            "line": 6,
            "match": {
              "location": "/Users/lisa/Desktop/JavaScript-kurs/coffeeMachine/cucumber-exempel-2/coffee-machine/step-definitions/coffee-machine.js:53"
            }
          },
          {
            "arguments": [],
            "keyword": "And ",
            "name": "that the machine has lactosfree milk",
            "result": {
              "status": "passed",
              "duration": 47752
            },
            "line": 7,
            "match": {
              "location": "/Users/lisa/Desktop/JavaScript-kurs/coffeeMachine/cucumber-exempel-2/coffee-machine/step-definitions/coffee-machine.js:87"
            }
          },
          {
            "arguments": [],
            "keyword": "Given ",
            "name": "that user wants to buy cappucino with card",
            "result": {
              "status": "undefined"
            },
            "line": 76
          },
          {
            "arguments": [],
            "keyword": "When ",
            "name": "there is a electricity shortage",
            "result": {
              "status": "undefined"
            },
            "line": 77
          },
          {
            "arguments": [],
            "keyword": "And ",
            "name": "the coffee-machine goes offline for some time",
            "result": {
              "status": "undefined"
            },
            "line": 78
          },
          {
            "arguments": [],
            "keyword": "Then ",
            "name": "the machine won't produce cappucino because of risk of bacteria in warm milk",
            "result": {
              "status": "undefined"
            },
            "line": 79
          },
          {
            "arguments": [],
            "keyword": "And ",
            "name": "the card-reader will send a pre-programmed message to who-evers responsible for the card-reader",
            "result": {
              "status": "undefined"
            },
            "line": 80
          },
          {
            "arguments": [],
            "keyword": "After ",
            "result": {
              "status": "passed",
              "duration": 729131512
            },
            "hidden": true,
            "match": {
              "location": "/Users/lisa/Desktop/JavaScript-kurs/coffeeMachine/cucumber-exempel-2/coffee-machine/node_modules/selenium-cucumber-js/runtime/world.js:250"
            }
          }
        ],
        "tags": [],
        "type": "scenario"
      },
      {
        "id": "coffee-machine;user-wants-to-buy-regular-coffee-but-there-is-not-enough-beans",
        "keyword": "Scenario",
        "line": 82,
        "name": "User wants to buy regular coffee but there is not enough beans",
        "steps": [
          {
            "arguments": [],
            "keyword": "Given ",
            "name": "that the machine is plugged in",
            "result": {
              "status": "passed",
              "duration": 90874
            },
            "line": 5,
            "match": {
              "location": "/Users/lisa/Desktop/JavaScript-kurs/coffeeMachine/cucumber-exempel-2/coffee-machine/step-definitions/coffee-machine.js:36"
            }
          },
          {
            "arguments": [],
            "keyword": "And ",
            "name": "that water is available",
            "result": {
              "status": "passed",
              "duration": 52220
            },
            "line": 6,
            "match": {
              "location": "/Users/lisa/Desktop/JavaScript-kurs/coffeeMachine/cucumber-exempel-2/coffee-machine/step-definitions/coffee-machine.js:53"
            }
          },
          {
            "arguments": [],
            "keyword": "And ",
            "name": "that the machine has lactosfree milk",
            "result": {
              "status": "passed",
              "duration": 66183
            },
            "line": 7,
            "match": {
              "location": "/Users/lisa/Desktop/JavaScript-kurs/coffeeMachine/cucumber-exempel-2/coffee-machine/step-definitions/coffee-machine.js:87"
            }
          },
          {
            "arguments": [],
            "keyword": "Given ",
            "name": "that the user wants coffee",
            "result": {
              "status": "undefined"
            },
            "line": 83
          },
          {
            "arguments": [],
            "keyword": "And ",
            "name": "that there is less than 14 grams coffeebeans left in coffeebean-container",
            "result": {
              "status": "undefined"
            },
            "line": 84
          },
          {
            "arguments": [],
            "keyword": "When ",
            "name": "the user sees the coffee-menu on screen",
            "result": {
              "status": "undefined"
            },
            "line": 85
          },
          {
            "arguments": [],
            "keyword": "Then ",
            "name": "the machine shows the alternatives that uses regular coffeebeans as shadowed",
            "result": {
              "status": "undefined"
            },
            "line": 86
          },
          {
            "arguments": [],
            "keyword": "And ",
            "name": "un-choosable",
            "result": {
              "status": "undefined"
            },
            "line": 87
          },
          {
            "arguments": [],
            "keyword": "After ",
            "result": {
              "status": "passed",
              "duration": 722470987
            },
            "hidden": true,
            "match": {
              "location": "/Users/lisa/Desktop/JavaScript-kurs/coffeeMachine/cucumber-exempel-2/coffee-machine/node_modules/selenium-cucumber-js/runtime/world.js:250"
            }
          }
        ],
        "tags": [],
        "type": "scenario"
      },
      {
        "id": "coffee-machine;user-wants-to-buy-a-drink-which-contains-milk,-but-there-is-not-enough-milk-left",
        "keyword": "Scenario",
        "line": 89,
        "name": "User wants to buy a drink which contains milk, but there is not enough milk left",
        "steps": [
          {
            "arguments": [],
            "keyword": "Given ",
            "name": "that the machine is plugged in",
            "result": {
              "status": "passed",
              "duration": 92219
            },
            "line": 5,
            "match": {
              "location": "/Users/lisa/Desktop/JavaScript-kurs/coffeeMachine/cucumber-exempel-2/coffee-machine/step-definitions/coffee-machine.js:36"
            }
          },
          {
            "arguments": [],
            "keyword": "And ",
            "name": "that water is available",
            "result": {
              "status": "passed",
              "duration": 50708
            },
            "line": 6,
            "match": {
              "location": "/Users/lisa/Desktop/JavaScript-kurs/coffeeMachine/cucumber-exempel-2/coffee-machine/step-definitions/coffee-machine.js:53"
            }
          },
          {
            "arguments": [],
            "keyword": "And ",
            "name": "that the machine has lactosfree milk",
            "result": {
              "status": "passed",
              "duration": 49303
            },
            "line": 7,
            "match": {
              "location": "/Users/lisa/Desktop/JavaScript-kurs/coffeeMachine/cucumber-exempel-2/coffee-machine/step-definitions/coffee-machine.js:87"
            }
          },
          {
            "arguments": [],
            "keyword": "Given ",
            "name": "that user want drink with milk",
            "result": {
              "status": "undefined"
            },
            "line": 90
          },
          {
            "arguments": [],
            "keyword": "And ",
            "name": "that there is to little milk left",
            "result": {
              "status": "undefined"
            },
            "line": 91
          },
          {
            "arguments": [],
            "keyword": "When ",
            "name": "the user sees the coffee-menu on screen",
            "result": {
              "status": "undefined"
            },
            "line": 92
          },
          {
            "arguments": [],
            "keyword": "Then ",
            "name": "the machine shows the alternatives containing milk as shadowed",
            "result": {
              "status": "undefined"
            },
            "line": 93
          },
          {
            "arguments": [],
            "keyword": "And ",
            "name": "un-choosable",
            "result": {
              "status": "undefined"
            },
            "line": 94
          },
          {
            "arguments": [],
            "keyword": "After ",
            "result": {
              "status": "passed",
              "duration": 771047785
            },
            "hidden": true,
            "match": {
              "location": "/Users/lisa/Desktop/JavaScript-kurs/coffeeMachine/cucumber-exempel-2/coffee-machine/node_modules/selenium-cucumber-js/runtime/world.js:250"
            }
          }
        ],
        "tags": [],
        "type": "scenario"
      }
    ],
    "id": "coffee-machine",
    "keyword": "Feature",
    "line": 1,
    "name": "Coffee-machine",
    "tags": [],
    "uri": "/Users/lisa/Desktop/JavaScript-kurs/coffeeMachine/cucumber-exempel-2/coffee-machine/features/coffee-machine.feature"
  }
]